scripts/__init__.py
scripts/evaluation.py
scripts/json2tloc.py
scripts/molmapsbbox.py
scripts/pdb_similarity_matrix.py
scripts/pymol_weight.py
scripts/train_optuna.py
tomotwin/__init__.py
tomotwin/embed_main.py
tomotwin/locate_main.py
tomotwin/map_main.py
tomotwin/pick_main.py
tomotwin/tools_main.py
tomotwin/train_main.py
tomotwin/modules/__init__.py
tomotwin/modules/common/__init__.py
tomotwin/modules/common/distances.py
tomotwin/modules/common/exceptions.py
tomotwin/modules/common/preprocess.py
tomotwin/modules/common/utils.py
tomotwin/modules/common/findmax/__init__.py
tomotwin/modules/common/findmax/findmax.py
tomotwin/modules/common/io/__init__.py
tomotwin/modules/common/io/cbox_format.py
tomotwin/modules/common/io/coords_format.py
tomotwin/modules/common/io/mrc_format.py
tomotwin/modules/common/io/reader_writer.py
tomotwin/modules/common/io/star_format.py
tomotwin/modules/inference/__init__.py
tomotwin/modules/inference/argparse_embed_ui.py
tomotwin/modules/inference/argparse_locate_ui.py
tomotwin/modules/inference/argparse_map_ui.py
tomotwin/modules/inference/argparse_pick_ui.py
tomotwin/modules/inference/boxer.py
tomotwin/modules/inference/distance_mapper.py
tomotwin/modules/inference/embed_ui.py
tomotwin/modules/inference/embedor.py
tomotwin/modules/inference/findmaxima_locator.py
tomotwin/modules/inference/locate_ui.py
tomotwin/modules/inference/locator.py
tomotwin/modules/inference/map_ui.py
tomotwin/modules/inference/mapper.py
tomotwin/modules/inference/pick_ui.py
tomotwin/modules/inference/reference_refinement.py
tomotwin/modules/inference/volumedata.py
tomotwin/modules/networks/GeneralizedMeanPooling.py
tomotwin/modules/networks/SiameseNet3D.py
tomotwin/modules/networks/__init__.py
tomotwin/modules/networks/networkmanager.py
tomotwin/modules/networks/resnet.py
tomotwin/modules/networks/torchmodel.py
tomotwin/modules/tools/__init__.py
tomotwin/modules/tools/embedding_mask.py
tomotwin/modules/tools/extract_reference.py
tomotwin_cryoet-0.9.1.2.dist-info/LICENSE
tomotwin_cryoet-0.9.1.2.dist-info/METADATA
tomotwin_cryoet-0.9.1.2.dist-info/WHEEL
tomotwin_cryoet-0.9.1.2.dist-info/entry_points.txt
tomotwin_cryoet-0.9.1.2.dist-info/top_level.txt
tomotwin_cryoet-0.9.1.2.dist-info/RECORD
