Metadata-Version: 2.1
Name: tomotwin-cryoet
Version: 0.9.1.2
Summary: Picking procedure for cryo em tomography
Home-page: https://github.com/MPI-Dortmund/tomotwin-cryoet
Author: Gavin Rice, Thorsten Wagner, Markus Stabrin
Author-email: thorsten.wagner@mpi-dortmund.mpg.de
License: Mozilla Public License Version 2.0
Requires-Python: >=3.7.0
License-File: LICENSE
Requires-Dist: mrcfile
Requires-Dist: tensorboard
Requires-Dist: numpy>=1.20.0
Requires-Dist: scikit-learn
Requires-Dist: scikit-image
Requires-Dist: pystardb>=0.4.2
Requires-Dist: pandas
Requires-Dist: numexpr>=2.8.4
Requires-Dist: numba
Requires-Dist: tabulate
Requires-Dist: setuptools_scm
Requires-Dist: tqdm
